zsindy/__init__.py
zsindy/dynamical_models.py
zsindy/experiments.py
zsindy/ml_module.py
zsindy/plotting.py
zsindy-0.1.1.dist-info/METADATA
zsindy-0.1.1.dist-info/WHEEL
zsindy-0.1.1.dist-info/top_level.txt
zsindy-0.1.1.dist-info/RECORD
