Metadata-Version: 2.1
Name: zsindy
Version: 0.1.1
Summary: A Bayesian statistical mechanical approach to sparse equation discovery
Author: Joseph Bakarji and Andrei Klishin
Author-email: joseph.bakarji0@aub.edu.lb
Requires-Dist: cmcrameri ==1.7
Requires-Dist: matplotlib
Requires-Dist: numpy
Requires-Dist: pysindy ==1.7.5
Requires-Dist: scipy ==1.11.3
Requires-Dist: setuptools ==67.4.0
Requires-Dist: tqdm ==4.64.1
